easy_clash_tool/__init__.py
easy_clash_tool/clash.py
easy_clash_tool/main.py
easy_clash_tool-0.0.3.dist-info/METADATA
easy_clash_tool-0.0.3.dist-info/WHEEL
easy_clash_tool-0.0.3.dist-info/entry_points.txt
easy_clash_tool-0.0.3.dist-info/top_level.txt
easy_clash_tool-0.0.3.dist-info/RECORD
